{
  "$schema": "http://schema.management.azure.com/schemas/2015-01-01/deploymentParameters.json",
  "contentVersion": "1.0.0.0",
  "parameters": {
    "appServiceEnvironmentName": {
      "value": "mkasev2"
    },
    "existingAseLocation": {
      "value": "East US 2"
    },
    "existingKeyVaultName": {
      "value": "ase-kv"
    },
    "existingKeyVaultRG": {
      "value": "asev2-rg"
    },
    "keyVaultSecretName": {
      "value": "asecert"
    },
    "certificateNamePrefix": {
      "value": "mk"
    },
    "certificateThumbprint":{
      "value": "479BB6A66EB50AEEA4248CB4216433A01720D747"
    }
  }
}